adafruit_requests.py
adafruit_circuitpython_requests-4.1.7.dist-info/LICENSE
adafruit_circuitpython_requests-4.1.7.dist-info/METADATA
adafruit_circuitpython_requests-4.1.7.dist-info/WHEEL
adafruit_circuitpython_requests-4.1.7.dist-info/top_level.txt
adafruit_circuitpython_requests-4.1.7.dist-info/RECORD
