Metadata-Version: 2.1
Name: adafruit-circuitpython-requests
Version: 4.1.7
Summary: A requests-like library for web interfacing
Author-email: Adafruit Industries <circuitpython@adafruit.com>
License: MIT
Project-URL: Homepage, https://github.com/adafruit/Adafruit_CircuitPython_Requests
Keywords: adafruit,blinka,circuitpython,micropython,requests,requests,,networking
Classifier: Intended Audience :: Developers
Classifier: Topic :: Software Development :: Libraries
Classifier: Topic :: Software Development :: Embedded Systems
Classifier: Topic :: System :: Hardware
Classifier: License :: OSI Approved :: MIT License
Classifier: Programming Language :: Python :: 3
License-File: LICENSE
Requires-Dist: Adafruit-Blinka
Requires-Dist: Adafruit-Circuitpython-ConnectionManager
Provides-Extra: optional
Requires-Dist: requests; extra == "optional"
